classifier_yan_zabab/__init__.py
classifier_yan_zabab/command_line.py
classifier_yan_zabab/module.py
classifier_yan_zabab-0.5.dist-info/METADATA
classifier_yan_zabab-0.5.dist-info/WHEEL
classifier_yan_zabab-0.5.dist-info/entry_points.txt
classifier_yan_zabab-0.5.dist-info/top_level.txt
classifier_yan_zabab-0.5.dist-info/RECORD
