Metadata-Version: 2.1
Name: classifier-yan-zabab
Version: 0.5
Summary: Example Package
Home-page: http://github.com/theKirill/GensimSample
Author: Yanyushkin
Author-email: k.a.yanushkin@gmail.com
License: MIT
Keywords: intents
Platform: UNKNOWN
Classifier: Development Status :: 3 - Alpha
Classifier: License :: OSI Approved :: MIT License
Classifier: Programming Language :: Python :: 2.7
Classifier: Topic :: Text Processing :: Linguistic
